pagame/__init__.py
pagame/__main__.py
pagame/contestants.py
pagame/draw.py
pagame/game.py
pagame/settings.py
pagame/sound.py
pagame/lookup/icons/add.png
pagame/lookup/icons/continue.png
pagame/lookup/icons/icon.icns
pagame/lookup/icons/icon.ico
pagame/lookup/icons/pause.png
pagame/lookup/icons/play.png
pagame/lookup/icons/power.png
pagame/lookup/icons/skip.png
pagame/lookup/icons/volume-down.png
pagame/lookup/icons/volume-up.png
pagame/lookup/textfiles/categories.txt
pagame/lookup/textfiles/likely_to.txt
pagame/lookup/textfiles/lyrics.txt
pagame-1.1.3.dist-info/LICENSE
pagame-1.1.3.dist-info/METADATA
pagame-1.1.3.dist-info/WHEEL
pagame-1.1.3.dist-info/entry_points.txt
pagame-1.1.3.dist-info/top_level.txt
pagame-1.1.3.dist-info/RECORD
