Metadata-Version: 2.1
Name: pagame
Version: 1.1.3
Summary: Party games for small groups.
Home-page: https://github.com/hallvardnmbu/pagame.git
Author: Hallvard Høyland Lavik
License: MIT
Classifier: Development Status :: 4 - Beta
Classifier: License :: OSI Approved :: MIT License
Classifier: Programming Language :: Python :: 3.12
Requires-Python: >=3.12
License-File: LICENSE
Requires-Dist: pyqt5
Requires-Dist: pygame
Requires-Dist: spotipy
Requires-Dist: deep-translator
Requires-Dist: gtts
